Workbook

Sheet Sheet1
A11: TAX INVOICE
A13: To, | C13: Date : 05-05-2026
A14: NEO ITURKAA ENTERPRISES. | C14: Invoice No. 004/2026-27
A15: ADD :- Office:- 101 1st Floor, Arihant Royale, Vaishali Nagar,
A16: Balrajeshwar Marg, Mulund (west) Mumbai :- 400080
A17: Pan No. : AAJFN6629D
A18: GST No. : 27AAJFN6629D1Z5
A21: Name of Work:-Reainforcemant Work.
A22: Name Of Project :- Tower D Wing Galaxy Maplewood -Airoli.
A23: Subject :- REF NO. : 20
A26: Sr. No. | B26: Description | C26: Amount
A28: 1 | B28: 37Th Slab Reinforcement Work done Amount | C28: =Sheet2!J26 -> 340000
A34: 2 | B34: Taxable Amount
B35: Add CGST@9% | C35: =C28*9% -> 30600
B36: Add SGST@9% | C36: =C28*9% -> 30600
B38: Net Payable Amount | C38: =SUM(C28:C37) -> 401200
A42: NAME :- RCR ENTERPRISES FOR | C42: RCR ENTERPRISES
A43: A/C :- 088405500559
A44: IFSC :- ICIC0000884
C45: AUTHORISED SIGNATORY

Sheet Sheet2
A7: `
A8: To, | I8: =Sheet1!C13 -> Date : 05-05-2026
A9: =Sheet1!A14 -> NEO ITURKAA ENTERPRISES. | I9: =Sheet1!C14 -> Invoice No. 004/2026-27
A10: =Sheet1!A15 -> ADD :- Office:- 101 1st Floor, Arihant Royale, Vaishali Nagar,
A11: =Sheet1!A16 -> Balrajeshwar Marg, Mulund (west) Mumbai :- 400080
A13: =Sheet1!A22 -> Name Of Project :- Tower D Wing Galaxy Maplewood -Airoli.
A14: =Sheet1!A21 -> Name of Work:-Reainforcemant Work.
A16: =Sheet1!A23 -> Subject :- REF NO. : 20
A17: W. O. No. :-GALAXY/NEOITURKAA/2025-26/06
A19: Sr. No | B19: Description | C19: Unit | D19: W.O. | E19: Rate | F19: Previous | G19: This Bill | H19: Cumulative | I19: Previous | J19: This Bill | K19: Previous
D20: Qty. | F20: Quantity | G20: Quantity | H20: Quantity | I20: Amount | J20: Amount | K20: Amount
A22: 1 | B22: Reinforcement Work Done. | C22: Sft. | D22: ='Tower C Wing'!D8:E8 -> 184464 | E22: ='Tower C Wing'!G8 -> 49.603175 | F22: ='Tower C Wing'!G41 -> 7110000 | G22: ='Tower C Wing'!H41 -> 340000 | H22: =F22+G22 -> 7450000 | I22: ='Tower C Wing'!G41 -> 7110000 | J22: =G22 -> 340000 | K22: =I22+J22 -> 7450000
A23: 2 | B23: Dept. Fitter Supply. | C23: Nos. | E23: =supply!E20 -> 1100 | F23: 0 | G23: 0 | H23: =F23+G23 -> 0 | I23: =F23*E23 -> 0 | J23: =G23*E23 -> 0 | K23: =I23+J23 -> 0
A24: 3 | B24: Dept. Fitter Helper Supply. | C24: Nos. | E24: =supply!G20 -> 800 | F24: 0 | G24: 0 | H24: =F24+G24 -> 0 | I24: =F24*E24 -> 0 | J24: =G24*E24 -> 0 | K24: =I24+J24 -> 0
B26: Total Amount | I26: =SUM(I22:I25) -> 7110000 | J26: =SUM(J22:J25) -> 340000 | K26: =SUM(K22:K25) -> 7450000
B28: ADD CGST @9%
B29: ADD CGST @9%
B30: LESS RETENTION@3% | I30: =I26*3% -> 213300 | J30: =J26*3% -> 10200 | K30: =I30+J30 -> 223500
I31: .
B32: Gross Amount | I32: =I26-I30 -> 6896700 | J32: =J26-J30 -> 329800 | K32: =K26-K30 -> 7226500
B33: TDS 1% Less amount | J33: =J26*1% -> 3400
B34: Balance | J34: =J32-J33 -> 326400

Sheet Tower C Wing
B2: =Sheet2!A9 -> NEO ITURKAA ENTERPRISES.
B3: =Sheet2!A14 -> Name of Work:-Reainforcemant Work.
B5: =Sheet2!A16 -> Subject :- REF NO. : 20
B6: BUA Building -
C7: Approximate Area
B8: CIVIL WORK | C8: Sft | D8: =6832*27 -> 184464 | F8: @ | G8: =I8/D8 -> 49.603175 | I8: =C41 -> 9150000
A10: Sr. | B10: Particulars | C10: Part | D10: Work done | G10: Amount
A11: No. | B11: of item
B12: Reainforcemant | D12: Previous | E12: This Bill | F12: Cumulative | G12: Previous | H12: This Bill | I12: Cumulative
B13: Work | D13: Quantity | E13: Quantity | F13: Quantity | G13: Amount | H13: Amount | I13: Amount
A14: 1 | B14: 16th slab | C14: 310000 | D14: 1 | E14: 0 | F14: =D14+E14 -> 1 | G14: =C14 -> 310000 | H14: 0 | I14: =G14+H14 -> 310000
A15: 2 | B15: 17th slab | C15: 340000 | D15: 1 | E15: 0 | F15: =D15+E15 -> 1 | G15: =C15 -> 340000 | H15: 0 | I15: =G15+H15 -> 340000
A16: 3 | B16: 18th slab | C16: 340000 | D16: 1 | E16: 0 | F16: =D16+E16 -> 1 | G16: =C16 -> 340000 | H16: 0 | I16: =G16+H16 -> 340000
A17: 4 | B17: 19th slab | C17: 340000 | D17: 1 | E17: 0 | F17: =D17+E17 -> 1 | G17: =C17 -> 340000 | H17: 0 | I17: =G17+H17 -> 340000
A18: 5 | B18: 20th slab | C18: 340000 | D18: 1 | E18: 0 | F18: =D18+E18 -> 1 | G18: =C18 -> 340000 | H18: 0 | I18: =G18+H18 -> 340000
A19: 6 | B19: 21st slab | C19: 340000 | D19: 1 | E19: 0 | F19: =D19+E19 -> 1 | G19: =C19 -> 340000 | H19: 0 | I19: =G19+H19 -> 340000
A20: 7 | B20: 22nd slab | C20: 340000 | D20: 1 | E20: 0 | F20: =D20+E20 -> 1 | G20: =C20 -> 340000 | H20: 0 | I20: =G20+H20 -> 340000
A21: 8 | B21: 23rd slab | C21: 340000 | D21: 1 | E21: 0 | F21: =D21+E21 -> 1 | G21: =C21 -> 340000 | H21: 0 | I21: =G21+H21 -> 340000
A22: 9 | B22: 24th slab | C22: 340000 | D22: 1 | E22: 0 | F22: =D22+E22 -> 1 | G22: =C22 -> 340000 | H22: 0 | I22: =G22+H22 -> 340000
A23: 10 | B23: 25th slab | C23: 340000 | D23: 1 | E23: 0 | F23: =D23+E23 -> 1 | G23: =C23 -> 340000 | H23: 0 | I23: =G23+H23 -> 340000
A24: 11 | B24: 26th slab | C24: 340000 | D24: 1 | E24: 0 | F24: =D24+E24 -> 1 | G24: =C24 -> 340000 | H24: 0 | I24: =G24+H24 -> 340000
A25: 12 | B25: 27th slab | C25: 340000 | D25: 1 | E25: 0 | F25: =D25+E25 -> 1 | G25: =C25 -> 340000 | H25: 0 | I25: =G25+H25 -> 340000
... A34: 21 | B34: 36th slab | C34: 340000 | D34: 1 | E34: 0 | F34: =D34+E34 -> 1 | G34: =C34 -> 340000 | H34: 0 | I34: =G34+H34 -> 340000
A35: 22 | B35: 37th slab | C35: 340000 | D35: 0 | E35: 1 | F35: =D35+E35 -> 1 | G35: 0 | H35: =C35 -> 340000 | I35: =G35+H35 -> 340000
A36: 23 | B36: 38th slab | C36: 340000 | D36: 0 | E36: 0 | F36: =D36+E36 -> 0 | G36: =F36 -> 0 | H36: =E36 -> 0 | I36: =G36+H36 -> 0
A37: 24 | B37: 39th slab | C37: 340000 | D37: 0 | E37: 0 | F37: =D37+E37 -> 0 | G37: =F37 -> 0 | H37: =E37 -> 0 | I37: =G37+H37 -> 0
A38: 25 | B38: Completion of Terrace Slab 40th slab | C38: 340000 | D38: 0 | E38: 0 | F38: =D38+E38 -> 0 | G38: =F38 -> 0 | H38: =E38 -> 0 | I38: =G38+H38 -> 0
A39: 26 | B39: Completion of LMR, OHWT PARAPET WALL. | C39: 680000 | D39: 0 | E39: 0 | F39: =D39+E39 -> 0 | G39: =F39 -> 0 | H39: =E39 -> 0 | I39: =G39+H39 -> 0
B41: TOTAL AMOUNT | C41: =SUM(C14:C40) -> 9150000 | D41: =SUM(D14:D40) -> 21 | E41: =SUM(E14:E40) -> 1 | F41: =SUM(F14:F40) -> 22 | G41: =SUM(G14:G40) -> 7110000 | H41: =SUM(H14:H40) -> 340000 | I41: =SUM(I14:I40) -> 7450000

Sheet supply
A3: =Sheet2!A9 -> NEO ITURKAA ENTERPRISES.
A4: Labour's Supply MARCH 2026 | I4: =Sheet2!I8 -> Date : 05-05-2026
A5: Contractar : - RCR ENTERPRISES
A6: Date | B6: Challan No. | C6: Description Contract basis work | D6: Fitter | E6: Hours | F6: Total Fitter Hours | G6: Fitter Helfar | H6: Hours | I6: Total Lebour Hours | J6: Remarks
C16: Total (Nos) | F16: =SUM(F7:F15) -> 0 | I16: =SUM(I7:I15) -> 0
E18: FITTER | G18: FITTER HELFAR
C19: Nos | E19: =F16 -> 0 | G19: 0
C20: Rate | E20: 1100 | G20: 800
C21: TOTAL AMOUNT | E21: =E20*E19 -> 0 | G21: =G20*G19 -> 0 | I21: =E21*G21 -> 0

Sheet Balance sheet
A3: SR. NO | B3: DATE | C3: RA BILLS | D3: BILL AMOUNT | E3: RETENTION 3% | F3: AMOUNT | G3: ACCOUNT CREDITED | H3: 1%TDS BALANCE | I3: ADVANCE | J3: BALANCE | K3: GST AMOUNT | L3: BALANCE
A4: 1 | B4: 45848 | G4: 150000
A5: 2 | B5: 45873 | G5: 200000
C6: 05-08-2025 BILL NO.01 DIGHA GALAXY.
D7: ='[1]Balance sheet'!$D$7:$D$8 -> 650000 | E7: =D7*3% -> 19500 | F7: =D7-E7 -> 630500 | H7: =D7*1% -> 6500 | K7: =D7*18% -> 117000
B9: TOTAL AMOUNT | D9: =SUM(D4:D8) -> 650000 | E9: =SUM(E4:E8) -> 19500 | F9: =SUM(F4:F8) -> 630500 | G9: =SUM(G4:G8) -> 350000 | H9: =SUM(H4:H8) -> 6500 | I9: =G9+H9 -> 356500 | J9: =F9-I9 -> 274000 | K9: =SUM(K6:K8) -> 117000 | L9: =J9+K9 -> 391000
A10: 3 | B10: 45889 | G10: 394250
C11: 22-08-2025 BILL NO.02 DIGHA GALAXY.
D12: =[2]Sheet1!$C$28 -> 340000 | E12: =D12*3% -> 10200 | F12: =D12-E12 -> 329800 | H12: =D12*1% -> 3400 | K12: =D12*18% -> 61200
B14: TOTAL AMOUNT | D14: =SUM(D9:D13) -> 990000 | E14: =SUM(E9:E13) -> 29700 | F14: =SUM(F9:F13) -> 960300 | G14: =SUM(G9:G13) -> 744250 | H14: =SUM(H9:H13) -> 9900 | I14: =G14+H14 -> 754150 | J14: =F14-I14 -> 206150 | K14: =SUM(K9:K13) -> 178200 | L14: =J14+K14 -> 384350
C15: 04-09-2025 BILL NO.03 DIGHA GALAXY.
D16: =[3]Sheet1!$C$27 -> 340000 | E16: =D16*3% -> 10200 | F16: =D16-E16 -> 329800 | H16: =D16*1% -> 3400 | K16: =D16*18% -> 61200
B18: TOTAL AMOUNT | D18: =SUM(D13:D17) -> 1330000 | E18: =SUM(E13:E17) -> 39900 | F18: =SUM(F14:F17) -> 1290100 | G18: =SUM(G14:G17) -> 744250 | H18: =SUM(H13:H17) -> 13300 | I18: =G18+H18 -> 757550 | J18: =F18-I18 -> 532550 | K18: =SUM(K14:K17) -> 239400 | L18: =J18+K18 -> 771950
A19: 4 | B19: 17/09/2025 | F19: NEFT | G19: 384350
C20: 16-09-2025 BILL NO.04 DIGHA GALAXY.
D21: =[4]Sheet1!$C$27 -> 340000 | E21: =D21*3% -> 10200 | F21: =D21-E21 -> 329800 | H21: =D21*1% -> 3400 | K21: =D21*18% -> 61200
B23: TOTAL AMOUNT | D23: =SUM(D18:D22) -> 1670000 | E23: =SUM(E18:E22) -> 50100 | F23: =SUM(F18:F22) -> 1619900 | G23: =SUM(G18:G22) -> 1128600 | H23: =SUM(H17:H22) -> 16700 | I23: =G23+H23 -> 1145300 | J23: =F23-I23 -> 474600 | K23: =SUM(K18:K22) -> 300600 | L23: =J23+K23 -> 775200
A24: 5 | B24: 24/09/2025 | F24: NEFT | G24: 387600
C25: 10-10-2025 BILL NO.05 DIGHA GALAXY.
D26: =[5]Sheet1!$C$27 -> 340000 | E26: =D26*3% -> 10200 | F26: =D26-E26 -> 329800 | H26: =D26*1% -> 3400 | K26: =D26*18% -> 61200
B28: TOTAL AMOUNT | D28: =SUM(D23:D27) -> 2010000 | E28: =SUM(E23:E27) -> 60300 | F28: =SUM(F23:F27) -> 1949700 | G28: =SUM(G23:G27) -> 1516200 | H28: =SUM(H22:H27) -> 20100 | I28: =G28+H28 -> 1536300 | J28: =F28-I28 -> 413400 | K28: =SUM(K23:K27) -> 361800 | L28: =J28+K28 -> 775200
A29: 6 | B29: 45818 | F29: NEFT | G29: 387600
C30: 23-10-2025 BILL NO.06 DIGHA GALAXY.
D31: =[6]Sheet1!$C$27 -> 340000 | E31: =D31*3% -> 10200 | F31: =D31-E31 -> 329800 | H31: =D31*1% -> 3400 | K31: =D31*18% -> 61200
B33: TOTAL AMOUNT | D33: =SUM(D28:D32) -> 2350000 | E33: =SUM(E28:E32) -> 70500 | F33: =SUM(F28:F32) -> 2279500 | G33: =SUM(G28:G32) -> 1903800 | H33: =SUM(H27:H32) -> 23500 | I33: =G33+H33 -> 1927300 | J33: =F33-I33 -> 352200 | K33: =SUM(K28:K32) -> 423000 | L33: =J33+K33 -> 775200
A34: 7 | B34: 29/10/2025 | F34: NEFT | G34: 387600
C35: 04-11-2025 BILL NO.07 DIGHA GALAXY.
D36: =[7]Sheet1!$C$28 -> 340000 | E36: =D36*3% -> 10200 | F36: =D36-E36 -> 329800 | H36: =D36*1% -> 3400 | K36: =D36*18% -> 61200
B38: TOTAL AMOUNT | D38: =SUM(D33:D37) -> 2690000 | E38: =SUM(E33:E37) -> 80700 | F38: =SUM(F33:F37) -> 2609300 | G38: =SUM(G33:G37) -> 2291400 | H38: =SUM(H33:H37) -> 26900 | I38: =G38+H38 -> 2318300 | J38: =F38-I38 -> 291000 | K38: =SUM(K33:K37) -> 484200 | L38: =J38+K38 -> 775200
A39: 8 | B39: 14/11/2025 | F39: NEFT | G39: 397800
C40: 16-11-2025 BILL NO.08 DIGHA GALAXY.
D41: =[8]Sheet1!$C$28 -> 340000 | E41: =D41*3% -> 10200 | F41: =D41-E41 -> 329800 | H41: =D41*1% -> 3400 | K41: =D41*18% -> 61200
B43: TOTAL AMOUNT | D43: =SUM(D38:D42) -> 3030000 | E43: =SUM(E38:E42) -> 90900 | F43: =SUM(F38:F42) -> 2939100 | G43: =SUM(G38:G42) -> 2689200 | H43: =SUM(H38:H42) -> 30300 | I43: =G43+H43 -> 2719500 | J43: =F43-I43 -> 219600 | K43: =SUM(K38:K42) -> 545400 | L43: =J43+K43 -> 765000
A44: 9 | B44: 20/11/2025 | F44: NEFT | G44: 377400
C45: 27-11-2025 BILL NO.09 DIGHA GALAXY.
D46: =[9]Sheet1!$C$28 -> 340000 | E46: =D46*3% -> 10200 | F46: =D46-E46 -> 329800 | H46: =D46*1% -> 3400 | K46: =D46*18% -> 61200
B48: TOTAL AMOUNT | D48: =SUM(D43:D47) -> 3370000 | E48: =SUM(E43:E47) -> 101100 | F48: =SUM(F43:F47) -> 3268900 | G48: =SUM(G43:G47) -> 3066600 | H48: =SUM(H43:H47) -> 33700 | I48: =G48+H48 -> 3100300 | J48: =F48-I48 -> 168600 | K48: =SUM(K43:K47) -> 606600 | L48: =J48+K48 -> 775200
A49: 10 | B49: 45912 | F49: NEFT | G49: 387600
C50: 12-12-2025 BILL NO.10 DIGHA GALAXY.
D51: =[10]Sheet1!$C$28 -> 340000 | E51: =D51*3% -> 10200 | F51: =D51-E51 -> 329800 | H51: =D51*1% -> 3400 | K51: =D51*18% -> 61200
B53: TOTAL AMOUNT | D53: =SUM(D48:D52) -> 3710000 | E53: =SUM(E48:E52) -> 111300 | F53: =SUM(F48:F52) -> 3598700 | G53: =SUM(G48:G52) -> 3454200 | H53: =SUM(H48:H52) -> 37100 | I53: =G53+H53 -> 3491300 | J53: =F53-I53 -> 107400 | K53: =SUM(K48:K52) -> 667800 | L53: =J53+K53 -> 775200
A54: 11 | B54: 19/12/2025 | F54: NEFT | G54: 387600
C55: 21-12-2025 BILL NO.11 DIGHA GALAXY.
D56: =[11]Sheet1!$C$28 -> 340000 | E56: =D56*3% -> 10200 | F56: =D56-E56 -> 329800 | H56: =D56*1% -> 3400 | K56: =D56*18% -> 61200
B58: TOTAL AMOUNT | D58: =SUM(D53:D57) -> 4050000 | E58: =SUM(E53:E57) -> 121500 | F58: =SUM(F53:F57) -> 3928500 | G58: =SUM(G53:G57) -> 3841800 | H58: =SUM(H53:H57) -> 40500 | I58: =G58+H58 -> 3882300 | J58: =F58-I58 -> 46200 | K58: =SUM(K53:K57) -> 729000 | L58: =J58+K58 -> 775200
C59: 29-12-2025 BILL NO.12 DIGHA GALAXY.
D60: =[12]Sheet1!$C$28 -> 340000 | E60: =D60*3% -> 10200 | F60: =D60-E60 -> 329800 | H60: =D60*1% -> 3400 | K60: =D60*18% -> 61200
B62: TOTAL AMOUNT | D62: =SUM(D58:D61) -> 4390000 | E62: =SUM(E58:E61) -> 131700 | F62: =SUM(F58:F61) -> 4258300 | G62: =SUM(G58:G61) -> 3841800 | H62: =SUM(H58:H61) -> 43900 | I62: =G62+H62 -> 3885700 | J62: =F62-I62 -> 372600 | K62: =SUM(K58:K61) -> 790200 | L62: =J62+K62 -> 1162800
A63: 12 | B63: 46023 | F63: NEFT | G63: 387600
C64: 07-01-2026 BILL NO.13 DIGHA GALAXY.
D65: =[13]Sheet1!$C$28 -> 340000 | E65: =D65*3% -> 10200 | F65: =D65-E65 -> 329800 | H65: =D65*1% -> 3400 | K65: =D65*18% -> 61200
B67: TOTAL AMOUNT | D67: =SUM(D62:D66) -> 4730000 | E67: =SUM(E62:E66) -> 141900 | F67: =SUM(F62:F66) -> 4588100 | G67: =SUM(G62:G66) -> 4229400 | H67: =SUM(H62:H66) -> 47300 | I67: =G67+H67 -> 4276700 | J67: =F67-I67 -> 311400 | K67: =SUM(K62:K66) -> 851400 | L67: =J67+K67 -> 1162800
A68: 13 | B68: 20/01/2026 | F68: NEFT | G68: 775200
A69: 14 | B69: 22/01/2026 | F69: NEFT | G69: 387600
C70: 01-02-2026 BILL NO.14 DIGHA GALAXY.
D71: =[14]Sheet1!$C$28 -> 680000 | E71: =D71*3% -> 20400 | F71: =D71-E71 -> 659600 | H71: =D71*1% -> 6800 | K71: =D71*18% -> 122400
B73: TOTAL AMOUNT | D73: =SUM(D67:D72) -> 5410000 | E73: =SUM(E67:E72) -> 162300 | F73: =SUM(F67:F72) -> 5247700 | G73: =SUM(G67:G72) -> 5392200 | H73: =SUM(H67:H72) -> 54100 | I73: =G73+H73 -> 5446300 | J73: =F73-I73 -> -198600 | K73: =SUM(K67:K72) -> 973800 | L73: =J73+K73 -> 775200
A74: 15 | B74: 46297 | F74: NEFT | G74: 775200
C75: 09-02-2026 BILL NO.15 DIGHA GALAXY.
D76: =[15]Sheet1!$C$28 -> 340000 | E76: =D76*3% -> 10200 | F76: =D76-E76 -> 329800 | H76: =D76*1% -> 3400 | K76: =D76*18% -> 61200
B78: TOTAL AMOUNT | D78: =SUM(D72:D77) -> 5750000 | E78: =SUM(E72:E77) -> 172500 | F78: =SUM(F72:F77) -> 5577500 | G78: =SUM(G72:G77) -> 6167400 | H78: =SUM(H72:H77) -> 57500 | I78: =G78+H78 -> 6224900 | J78: =F78-I78 -> -647400 | K78: =SUM(K72:K77) -> 1035000 | L78: =J78+K78 -> 387600
C79: 20-02-2026 BILL NO.16 DIGHA GALAXY.
D80: =[16]Sheet1!$C$28 -> 340000 | E80: =D80*3% -> 10200 | F80: =D80-E80 -> 329800 | H80: =D80*1% -> 3400 | K80: =D80*18% -> 61200
B82: TOTAL AMOUNT | D82: =SUM(D77:D81) -> 6090000 | E82: =SUM(E77:E81) -> 182700 | F82: =SUM(F77:F81) -> 5907300 | G82: =SUM(G77:G81) -> 6167400 | H82: =SUM(H77:H81) -> 60900 | I82: =G82+H82 -> 6228300 | J82: =F82-I82 -> -321000 | K82: =SUM(K77:K81) -> 1096200 | L82: =J82+K82 -> 775200
A83: 16 | B83: 27/02/2026 | F83: NEFT | G83: 387600
C84: 07-03-2026 BILL NO.17 DIGHA GALAXY.
D85: =[17]Sheet1!$C$28 -> 340000 | E85: =D85*3% -> 10200 | F85: =D85-E85 -> 329800 | H85: =D85*1% -> 3400 | K85: =D85*18% -> 61200
B87: TOTAL AMOUNT | D87: =SUM(D82:D86) -> 6430000 | E87: =SUM(E82:E86) -> 192900 | F87: =SUM(F82:F86) -> 6237100 | G87: =SUM(G82:G86) -> 6555000 | H87: =SUM(H82:H86) -> 64300 | I87: =G87+H87 -> 6619300 | J87: =F87-I87 -> -382200 | K87: =SUM(K82:K86) -> 1157400 | L87: =J87+K87 -> 775200
A88: 17 | B88: 46091 | F88: NEFT | G88: 387600
A89: 18 | B89: 46101 | G89: 387600
C90: 27-03-2026 BILL NO.18 DIGHA GALAXY.
D91: =[18]Sheet1!$C$28 -> 340000 | E91: =D91*3% -> 10200 | F91: =D91-E91 -> 329800 | H91: =D91*1% -> 3400 | K91: =D91*18% -> 61200
B93: TOTAL AMOUNT | D93: =SUM(D87:D92) -> 6770000 | E93: =SUM(E87:E92) -> 203100 | F93: =SUM(F87:F92) -> 6566900 | G93: =SUM(G87:G92) -> 7330200 | H93: =SUM(H87:H92) -> 67700 | I93: =G93+H93 -> 7397900 | J93: =F93-I93 -> -831000 | K93: =SUM(K87:K92) -> 1218600 | L93: =J93+K93 -> 387600
C94: 09-04-2026 BILL NO.19 DIGHA GALAXY.
D95: =[19]Sheet1!$C$28 -> 340000 | E95: =D95*3% -> 10200 | F95: =D95-E95 -> 329800 | H95: =D95*1% -> 3400 | K95: =D95*18% -> 61200
B97: TOTAL AMOUNT | D97: =SUM(D93:D96) -> 7110000 | E97: =SUM(E93:E96) -> 213300 | F97: =SUM(F93:F96) -> 6896700 | G97: =SUM(G93:G96) -> 7330200 | H97: =SUM(H93:H96) -> 71100 | I97: =G97+H97 -> 7401300 | J97: =F97-I97 -> -504600 | K97: =SUM(K93:K96) -> 1279800 | L97: =J97+K97 -> 775200
A98: 19 | B98: 46128 | F98: NEFT | G98: 387600
C99: 05-05-2026 BILL NO.20 DIGHA GALAXY.
D100: =Sheet1!C28 -> 340000 | E100: =D100*3% -> 10200 | F100: =D100-E100 -> 329800 | H100: =D100*1% -> 3400 | K100: =D100*18% -> 61200
B102: TOTAL AMOUNT | D102: =SUM(D97:D101) -> 7450000 | E102: =SUM(E97:E101) -> 223500 | F102: =SUM(F97:F101) -> 7226500 | G102: =SUM(G97:G101) -> 7717800 | H102: =SUM(H97:H101) -> 74500 | I102: =G102+H102 -> 7792300 | J102: =F102-I102 -> -565800 | K102: =SUM(K97:K101) -> 1341000 | L102: =J102+K102 -> 775200
