Workbook

Sheet Sheet1
A11: TAX INVOICE
A13: To, | C13: Date : 05-05-2026
A14: SSHIVAAY CONSTRUCTIONS. | C14: Invoice No. 007/2026-27
A15: ADD :- Office:- SANT KRUPA CHS LTD., FLAT NO.5, PLOT NO. 78, SECTOR - 19
A16: NERUL (EAST), NAVI MUMBAI - 400706
A17: Pan No. : AEXFS8040P
A18: GST No. : 27AEXFS8040P1ZW
A21: Name of Work:-Reainforcemant Work.
A22: Name Of Project :- BMC COLONY, BUILDING NO :- S3 VIKHROLI, MUMBAI
A23: Subject :- REF NO. : 01
A26: Sr. No. | B26: Description | C26: Amount
A28: 1 | B28: 15Th To 16Th Slab Reinforcement Work done Amount | C28: =Sheet2!J27 -> 250648
A34: 2 | B34: Taxable Amount
B35: Add CGST@9% | C35: =C28*9% -> 22558.32
B36: Add SGST@9% | C36: =C28*9% -> 22558.32
B38: Net Payable Amount | C38: =SUM(C28:C37) -> 295764.64
A42: NAME :- RCR ENTERPRISES FOR | C42: RCR ENTERPRISES
A43: A/C :- 088405500559
A44: IFSC :- ICIC0000884
C45: AUTHORISED SIGNATORY

Sheet Sheet2
A7: `
A8: To, | I8: =Sheet1!C13 -> Date : 05-05-2026
A9: =Sheet1!A14 -> SSHIVAAY CONSTRUCTIONS. | I9: =Sheet1!C14 -> Invoice No. 007/2026-27
A10: =Sheet1!A15 -> ADD :- Office:- SANT KRUPA CHS LTD., FLAT NO.5, PLOT NO. 78, SECTOR - 19
A11: =Sheet1!A16 -> NERUL (EAST), NAVI MUMBAI - 400706
A13: =Sheet1!A22 -> Name Of Project :- BMC COLONY, BUILDING NO :- S3 VIKHROLI, MUMBAI
A14: =Sheet1!A21 -> Name of Work:-Reainforcemant Work.
A16: =Sheet1!A23 -> Subject :- REF NO. : 01
A17: W. O. No. :-PARKSITE/SSHIVAAY/2026-27
A19: Sr. No | B19: Description | C19: Unit | D19: W.O. | E19: Rate | F19: Previous | G19: This Bill | H19: Cumulative | I19: Previous | J19: This Bill | K19: Previous
D20: Qty. | F20: Quantity | G20: Quantity | H20: Quantity | I20: Amount | J20: Amount | K20: Amount
A22: 1 | B22: S2 Reinforcement Work Done. | C22: Sft. | D22: ='Tower S2 Wing'!D8:E8 -> 314554 | E22: 53 | F22: ='Tower S3 Wing'!G23 -> 0 | G22: ='Tower S3 Wing'!C13 -> 0 | H22: =F22+G22 -> 0 | I22: ='Tower S3 Wing'!G23 -> 0 | J22: ='Tower S3 Wing'!H23 -> 0 | K22: =I22+J22 -> 0
A23: 2 | B23: S3 Reinforcement Work Done. | C23: Sft. | D23: ='Tower S3 Wing'!D8:E8 -> 24750 | E23: ='Tower S3 Wing'!G8 -> 52 | F23: ='Tower S3 Wing'!D24 -> 0 | G23: ='Tower S3 Wing'!E24 -> 4674 | H23: =F23+G23 -> 4674 | I23: ='Tower S3 Wing'!G24 -> 0 | J23: ='Tower S3 Wing'!H24 -> 243048 | K23: =I23+J23 -> 243048
A24: 3 | B24: Dept. Fitter Supply. | C24: Nos. | E24: =supply!E20 -> 1100 | F24: ='Tower S3 Wing'!G25 -> 0 | G24: =supply!E19 -> 6 | H24: =F24+G24 -> 6 | I24: =F24*E24 -> 0 | J24: =G24*E24 -> 6600 | K24: =I24+J24 -> 6600
A25: 4 | B25: Dept. Fitter Helper Supply. | C25: Nos. | E25: =supply!G20 -> 800 | F25: 0 | G25: =supply!G19 -> 1.25 | H25: =F25+G25 -> 1.25 | I25: =F25*E25 -> 0 | J25: =G25*E25 -> 1000 | K25: =I25+J25 -> 1000
B27: Total Amount | I27: =SUM(I23:I26) -> 0 | J27: =SUM(J23:J26) -> 250648 | K27: =SUM(K23:K26) -> 250648
B29: ADD CGST @9%
B30: ADD CGST @9%
B31: LESS RETENTION@0% | I31: =I27*3% -> 0 | J31: =J27*0% -> 0 | K31: =I31+J31 -> 0
I32: .
B33: Gross Amount | I33: =I27-I31 -> 0 | J33: =J27-J31 -> 250648 | K33: =K27-K31 -> 250648
B34: TDS 1% Less amount | J34: =J27*1% -> 2506.48
B35: Balance | J35: =J33-J34 -> 248141.52

Sheet Tower S2 Wing
B2: =Sheet2!A9 -> SSHIVAAY CONSTRUCTIONS.
B3: =Sheet2!A14 -> Name of Work:-Reainforcemant Work.
B5: =Sheet2!A16 -> Subject :- REF NO. : 01
B6: BUA Building - S2 BUILDING
C7: Approximate Area
B8: CIVIL WORK | C8: Sft | D8: =C40 -> 314554 | F8: @ | G8: 53 | I8: =D8*G8 -> 16671362
A10: Sr. | B10: Particulars | C10: Part | D10: Work done | G10: Amount
A11: No. | B11: of item
B12: Reainforcemant | D12: Previous | E12: This Bill | F12: Cumulative | G12: Previous | H12: This Bill | I12: Cumulative
B13: Work | D13: Quantity | E13: Quantity | F13: Quantity | G13: Amount | H13: Amount | I13: Amount
A14: 1 | B14: Raft Footing, Plint Beam | C14: 22728 | D14: 0 | E14: 0 | F14: 0 | G14: 0 | H14: 0 | I14: 0
A15: 2 | B15: 1st slab | C15: 17068 | D15: 0 | E15: 0 | F15: 0 | G15: 0 | H15: 0 | I15: =G15+H15 -> 0
A16: 3 | B16: 2nd slab | C16: 11946 | D16: 0 | E16: 0 | F16: 0 | G16: 0 | H16: 0 | I16: =G16+H16 -> 0
A17: 4 | B17: 3rd slab | C17: 11946 | D17: 0 | E17: 0 | F17: 0 | G17: 0 | H17: 0 | I17: =G17+H17 -> 0
A18: 5 | B18: 4th slab | C18: 11946 | D18: 0 | E18: 0 | F18: 0 | G18: 0 | H18: 0 | I18: =G18+H18 -> 0
A19: 6 | B19: 5th slab | C19: 11946 | D19: 0 | E19: 0 | F19: 0 | G19: 0 | H19: 0 | I19: =G19+H19 -> 0
A20: 7 | B20: 6th slab | C20: 11946 | D20: 0 | E20: 0 | F20: 0 | G20: 0 | H20: 0 | I20: =G20+H20 -> 0
A21: 8 | B21: 7th slab | C21: 11946 | D21: 0 | E21: 0 | F21: 0 | G21: 0 | H21: 0 | I21: =G21+H21 -> 0
A22: 9 | B22: 8th slab Refuge | C22: 11946 | D22: 0 | E22: 0 | F22: 0 | G22: 0 | H22: 0 | I22: =G22+H22 -> 0
A23: 10 | B23: 9th slab | C23: 11946 | D23: 0 | E23: 0 | F23: 0 | G23: 0 | H23: 0 | I23: =G23+H23 -> 0
A24: 11 | B24: 10th slab Refuge | C24: 11946 | D24: 0 | E24: 0 | F24: 0 | G24: 0 | H24: 0 | I24: =G24+H24 -> 0
A25: 12 | B25: 11th slab | C25: 11946 | D25: 0 | E25: 0 | F25: 0 | G25: 0 | H25: 0 | I25: =G25+H25 -> 0
A26: 13 | B26: 12th slab Refuge | C26: 11946 | D26: 0 | E26: 0 | F26: 0 | G26: 0 | H26: 0 | I26: =G26+H26 -> 0
... A36: 23 | B36: 22nd slab | C36: 11946 | D36: 0 | E36: 0 | F36: 0 | G36: 0 | H36: 0 | I36: =G36+H36 -> 0
A37: 27 | B37: Completion of Terrace Slab 23th slab | C37: 11946 | D37: 0 | E37: 0 | F37: 0 | G37: 0 | H37: =E37 -> 0 | I37: =G37+H37 -> 0
A38: 28 | B38: Completion of LMR, OHWT PARAPET WALL. | C38: 11946 | D38: 0 | E38: 0 | F38: 0 | G38: 0 | H38: =E38 -> 0 | I38: =G38+H38 -> 0
K39: 298855.8 | L39: 18971
B40: TOTAL AMOUNT | C40: =SUM(C14:C39) -> 314554 | D40: 0 | E40: 0 | F40: 0 | G40: =SUM(G14:G39) -> 0 | H40: =SUM(H14:H39) -> 0 | I40: =SUM(I14:I39) -> 0 | L40: 17068
K42: =K39-L42 -> 262816.8 | L42: =SUM(L39:L41) -> 36039
K46: =K42/22 -> 11946.218

Sheet Tower S3 Wing
B2: =Sheet2!A9 -> SSHIVAAY CONSTRUCTIONS.
B3: =Sheet2!A14 -> Name of Work:-Reainforcemant Work.
B5: =Sheet2!A16 -> Subject :- REF NO. : 01
B6: BUA Building -S3 BUILDING
C7: Approximate Area
B8: CIVIL WORK | C8: Sft | D8: =C24 -> 24750 | F8: @ | G8: 52 | I8: =D8*G8 -> 1287000
A10: Sr. | B10: Particulars | C10: Part | D10: Work done | G10: Amount
A11: No. | B11: of item
B12: Reainforcemant | D12: Previous | E12: This Bill | F12: Cumulative | G12: Previous | H12: This Bill | I12: Cumulative
B13: Work | D13: Quantity | E13: Quantity | F13: Quantity | G13: Amount | H13: Amount | I13: Amount
A14: 1 | B14: 15th slab | C14: 2750 | D14: 0 | E14: =C14 -> 2750 | F14: =D14+E14 -> 2750 | G14: =D14*G8 -> 0 | H14: =E14*G8 -> 143000 | I14: =G14+H14 -> 143000
A15: 2 | B15: 16th slab | C15: 2750 | D15: 0 | E15: 1924 | F15: =D15+E15 -> 1924 | G15: =D15*G8 -> 0 | H15: =E15*G8 -> 100048 | I15: =G15+H15 -> 100048
A16: 3 | B16: 17th slab | C16: 2750 | D16: 0 | E16: 0 | F16: 0 | G16: 0 | H16: 0 | I16: 0
A17: 4 | B17: 18th slab | C17: 2750 | D17: 0 | E17: 0 | F17: 0 | G17: 0 | H17: 0 | I17: =G17+H17 -> 0
A18: 5 | B18: 19th slab | C18: 2750 | D18: 0 | E18: 0 | F18: 0 | G18: 0 | H18: 0 | I18: =G18+H18 -> 0
A19: 6 | B19: 20th slab | C19: 2750 | D19: 0 | E19: 0 | F19: 0 | G19: 0 | H19: 0 | I19: =G19+H19 -> 0
A20: 7 | B20: 21st slab | C20: 2750 | D20: 0 | E20: 0 | F20: 0 | G20: 0 | H20: 0 | I20: =G20+H20 -> 0
A21: 11 | B21: Completion of Terrace Slab 22th slab | C21: 2750 | D21: 0 | E21: 0 | F21: 0 | G21: 0 | H21: =E21 -> 0 | I21: =G21+H21 -> 0
A22: 12 | B22: Completion of LMR, OHWT PARAPET WALL. | C22: 2750 | D22: 0 | E22: 0 | F22: 0 | G22: 0 | H22: =E22 -> 0 | I22: =G22+H22 -> 0
B24: TOTAL AMOUNT | C24: =SUM(C14:C23) -> 24750 | D24: 0 | E24: =SUM(E14:E23) -> 4674 | F24: 0 | G24: =SUM(G14:G23) -> 0 | H24: =SUM(H14:H23) -> 243048 | I24: =SUM(I14:I23) -> 243048

Sheet supply
A3: =Sheet2!A9 -> SSHIVAAY CONSTRUCTIONS.
A4: Labour's Supply May 2026 | I4: =Sheet2!I8 -> Date : 05-05-2026
A5: Contractar : - RCR ENTERPRISES
A6: Date | B6: Challan No. | C6: Description Contract basis work | D6: Fitter | E6: Hours | F6: Total Fitter Hours | G6: Fitter Helfar | H6: Hours | I6: Total Lebour Hours | J6: Remarks
A7: 46121 | B7: 9 | C7: 15th slab covring and slab Cheking work S3 building. | D7: 2 | E7: 8 | F7: =D7*E7 -> 16 | G7: 0 | H7: 0 | I7: =G7*H7 -> 0
A8: 46122 | B8: 9 | C8: 15Tth slab casting work complit 1 fitter and s2 building drain slab steel cutting banding fitter 4 | D8: 4 | E8: 8 | F8: =D8*E8 -> 32 | G8: 1 | H8: 10 | I8: =G8*H8 -> 10
F9: =D9*E9 -> 0 | I9: =G9*H9 -> 0
F10: =D10*E10 -> 0 | I10: =G10*H10 -> 0
F11: =D11*E11 -> 0 | I11: =G11*H11 -> 0
F12: =D12*E12 -> 0 | I12: =G12*H12 -> 0
F13: =D13*E13 -> 0 | I13: =G13*H13 -> 0
C16: Total (Nos) | F16: =SUM(F7:F15) -> 48 | I16: =SUM(I7:I15) -> 10
E18: FITTER | G18: FITTER HELFAR
C19: Nos | E19: =F16/8 -> 6 | G19: =I16/8 -> 1.25
C20: Rate | E20: 1100 | G20: 800
C21: TOTAL AMOUNT | E21: =E20*E19 -> 6600 | G21: =G20*G19 -> 1000 | I21: =E21+G21 -> 7600

Sheet Balance sheet
A3: SR. NO | B3: DATE | C3: RA BILLS | D3: BILL AMOUNT | E3: RETENTION 2% | F3: AMOUNT | G3: ACCOUNT CREDITED | H3: 1%TDS BALANCE | I3: ADVANCE | J3: BALANCE | K3: GST AMOUNT | L3: BALANCE
A4: 1 | B4: 46123 | F4: CASH ANSAT | G4: 15000
A5: 2 | B5: 46130 | F5: CASH ANSAT | G5: 15000
A6: 3 | B6: 46138 | F6: CASH ANSAT | G6: 15000
A7: 4 | B7: 46151 | F7: SANDIP ONLINE | G7: 22500
A8: 5 | B8: 46158 | F8: NEFT | G8: 141570
A9: 6 | B9: 46165 | F9: SANDIP ONLINE | G9: 24000
A10: 7 | B10: 46171 | F10: NEFT | G10: 99000
C11: 05-05-2026 BILL NO.01 VIKHROLI PARK SITE.
D12: =Sheet1!C28 -> 250648 | E12: =D12*0% -> 0 | F12: =D12-E12 -> 250648 | H12: =D12*1% -> 2506.48 | K12: =D12*18% -> 45116.64
B14: TOTAL AMOUNT | D14: =SUM(D4:D13) -> 250648 | E14: =SUM(E4:E13) -> 0 | F14: =SUM(F4:F13) -> 250648 | G14: =SUM(G4:G13) -> 332070 | H14: =SUM(H4:H13) -> 2506.48 | I14: =G14+H14 -> 334576.48 | J14: =F14-I14 -> -83928.48 | K14: =SUM(K11:K13) -> 45116.64 | L14: =J14+K14 -> -38811.84
